celery_healthcheck/__init__.py
celery_healthcheck/server.py
celery_healthcheck-0.2.0.dist-info/METADATA
celery_healthcheck-0.2.0.dist-info/WHEEL
celery_healthcheck-0.2.0.dist-info/licenses/LICENSE.md
celery_healthcheck-0.2.0.dist-info/RECORD
