Metadata-Version: 2.4
Name: celery-healthcheck
Version: 0.2.0
Summary: A lightweight HTTP health check server for Celery workers, designed to work with cloud platforms that only support TCP-based health probes
Project-URL: Repository, https://github.com/iloveitaly/celery-healthcheck
Author-email: Michael Bianco <mike@mikebian.co>
License: MIT
License-File: LICENSE.md
Keywords: azure,celery,fastapi,health-check,healthcheck,monitoring,worker
Requires-Python: >=3.9
Requires-Dist: celery>=5.5.0
Requires-Dist: fastapi>=0.115.12
Requires-Dist: uvicorn>=0.34.0
